SRC/__init__.py
SRC/__main__.py
SRC/main.py
dbt_docs_controller-1.0.0.dist-info/LICENSE.txt
dbt_docs_controller-1.0.0.dist-info/METADATA
dbt_docs_controller-1.0.0.dist-info/WHEEL
dbt_docs_controller-1.0.0.dist-info/entry_points.txt
dbt_docs_controller-1.0.0.dist-info/top_level.txt
dbt_docs_controller-1.0.0.dist-info/RECORD
