Metadata-Version: 2.1
Name: dbt-docs-controller
Version: 1.0.0
Summary: dbt-docs-controller streamlines dbt documentation by generating only the relevant models, sources, and components for concise, targeted user information.
Home-page: https://github.com/Govarthanans8/dbt-docs-controller/tree/main
Author: Govarthanan S
Classifier: Programming Language :: Python :: 3
Classifier: License :: OSI Approved :: MIT License
Classifier: Operating System :: OS Independent
Requires-Python: >=3.7
License-File: LICENSE.txt
